LICENSE
MANIFEST.in
README.txt
setup.py
story_chain/__init__.py
story_chain/flaskrunner.py
story_chain/launcher.py
story_chain/localdb.py
story_chain.egg-info/PKG-INFO
story_chain.egg-info/SOURCES.txt
story_chain.egg-info/dependency_links.txt
story_chain.egg-info/entry_points.txt
story_chain.egg-info/requires.txt
story_chain.egg-info/top_level.txt
story_chain/mod/__init__.py
story_chain/static/__init__.py
story_chain/templates/__init__.py
story_chain/ui/__init__.py
story_chain/ui/phonegap/__init__.py
story_chain/ui/phonegap/css/__init__.py
story_chain/ui/phonegap/img/__init__.py
story_chain/ui/phonegap/js/__init__.py
story_chain_res/__init__.py
story_chain_res/google_play_logo.png
story_chain_res/google_play_theme.png
story_chain_res/icon.ico
story_chain_res/local.db
story_chain_res/__pycache__/__init__.cpython-34.pyc