Metadata-Version: 1.1
Name: story-chain
Version: 0.1.1a1
Summary: muchu's android story chain app with jsonp web service
Home-page: https://github.com/muchu1983/story_chain
Author: MuChu Hsu
Author-email: muchu1983@gmail.com
License: BSD 3-Clause License
Download-URL: https://pypi.python.org/pypi/story_chain
Platform: python 3.4
Classifier: Development Status :: 3 - Alpha
Classifier: Environment :: Win32 (MS Windows)
Classifier: Environment :: X11 Applications :: GTK
Classifier: Intended Audience :: End Users/Desktop
Classifier: Intended Audience :: Developers
Classifier: License :: OSI Approved :: BSD License
Classifier: Natural Language :: Chinese (Traditional)
Classifier: Natural Language :: Chinese (Simplified)
Classifier: Natural Language :: English
Classifier: Operating System :: Microsoft :: Windows
Classifier: Operating System :: POSIX :: Linux
Classifier: Programming Language :: Python :: 3.3
Classifier: Topic :: Internet :: WWW/HTTP
